appdynamics_bindeps/__init__.py
appdynamics_bindeps/google/__init__.py
appdynamics_bindeps/google/protobuf/__init__.py
appdynamics_bindeps/google/protobuf/any_pb2.py
appdynamics_bindeps/google/protobuf/api_pb2.py
appdynamics_bindeps/google/protobuf/descriptor.py
appdynamics_bindeps/google/protobuf/descriptor.upb.c
appdynamics_bindeps/google/protobuf/descriptor.upb.h
appdynamics_bindeps/google/protobuf/descriptor.upb_minitable.c
appdynamics_bindeps/google/protobuf/descriptor.upb_minitable.h
appdynamics_bindeps/google/protobuf/descriptor.upbdefs.c
appdynamics_bindeps/google/protobuf/descriptor.upbdefs.h
appdynamics_bindeps/google/protobuf/descriptor_database.py
appdynamics_bindeps/google/protobuf/descriptor_pb2.py
appdynamics_bindeps/google/protobuf/descriptor_pool.py
appdynamics_bindeps/google/protobuf/duration_pb2.py
appdynamics_bindeps/google/protobuf/empty_pb2.py
appdynamics_bindeps/google/protobuf/field_mask_pb2.py
appdynamics_bindeps/google/protobuf/json_format.py
appdynamics_bindeps/google/protobuf/message.py
appdynamics_bindeps/google/protobuf/message_factory.py
appdynamics_bindeps/google/protobuf/proto.py
appdynamics_bindeps/google/protobuf/proto_builder.py
appdynamics_bindeps/google/protobuf/proto_json.py
appdynamics_bindeps/google/protobuf/reflection.py
appdynamics_bindeps/google/protobuf/runtime_version.py
appdynamics_bindeps/google/protobuf/service.py
appdynamics_bindeps/google/protobuf/service_reflection.py
appdynamics_bindeps/google/protobuf/source_context_pb2.py
appdynamics_bindeps/google/protobuf/struct_pb2.py
appdynamics_bindeps/google/protobuf/symbol_database.py
appdynamics_bindeps/google/protobuf/text_encoding.py
appdynamics_bindeps/google/protobuf/text_format.py
appdynamics_bindeps/google/protobuf/timestamp_pb2.py
appdynamics_bindeps/google/protobuf/type_pb2.py
appdynamics_bindeps/google/protobuf/unknown_fields.py
appdynamics_bindeps/google/protobuf/wrappers_pb2.py
appdynamics_bindeps/google/protobuf/compiler/__init__.py
appdynamics_bindeps_linux_aarch64-25.6.0.dist-info/METADATA
appdynamics_bindeps_linux_aarch64-25.6.0.dist-info/WHEEL
appdynamics_bindeps_linux_aarch64-25.6.0.dist-info/top_level.txt
appdynamics_bindeps_linux_aarch64-25.6.0.dist-info/RECORD
